odoo/addons/sale_order_product_availability_inline/README.rst
odoo/addons/sale_order_product_availability_inline/__init__.py
odoo/addons/sale_order_product_availability_inline/__manifest__.py
odoo/addons/sale_order_product_availability_inline/i18n/ca.po
odoo/addons/sale_order_product_availability_inline/i18n/es.po
odoo/addons/sale_order_product_availability_inline/i18n/it.po
odoo/addons/sale_order_product_availability_inline/i18n/sale_order_product_availability_inline.pot
odoo/addons/sale_order_product_availability_inline/models/__init__.py
odoo/addons/sale_order_product_availability_inline/models/product_product.py
odoo/addons/sale_order_product_availability_inline/models/product_template.py
odoo/addons/sale_order_product_availability_inline/models/sale.py
odoo/addons/sale_order_product_availability_inline/readme/CONTRIBUTORS.md
odoo/addons/sale_order_product_availability_inline/readme/DESCRIPTION.md
odoo/addons/sale_order_product_availability_inline/readme/USAGE.md
odoo/addons/sale_order_product_availability_inline/static/description/icon.png
odoo/addons/sale_order_product_availability_inline/static/description/index.html
odoo/addons/sale_order_product_availability_inline/tests/__init__.py
odoo/addons/sale_order_product_availability_inline/tests/test_sale_order_product_availability_inline.py
odoo/addons/sale_order_product_availability_inline/views/sale_views.xml
odoo_addon_sale_order_product_availability_inline-18.0.1.0.1.2.dist-info/METADATA
odoo_addon_sale_order_product_availability_inline-18.0.1.0.1.2.dist-info/WHEEL
odoo_addon_sale_order_product_availability_inline-18.0.1.0.1.2.dist-info/top_level.txt
odoo_addon_sale_order_product_availability_inline-18.0.1.0.1.2.dist-info/RECORD
